[
  {
    "name": "Vestido Zimmermann",
    "views": 7309,
    "collection": "Coleção A",
    "url": "vestido_zimmermann.mov"
  },
  {
    "name": "Gloss Hydra Gloss Lips 4ml",
    "views": 5341,
    "collection": "Coleção A",
    "url": "gloss_hydra_gloss_lips_4ml.mp4"
  },
  {
    "name": "VESTIDO LONGO SERENITY NITEROI",
    "views": 1927,
    "collection": "Coleção A",
    "url": "vestido_longo_serenity_niteroi.MOV"
  },
  {
    "name": "VESTIDO LONGO ROSA NITERÓI",
    "views": 8439,
    "collection": "Coleção A",
    "url": "vestido_longo_rosa.webm"
  },
  {
    "name": "Casaco Tannerie couro",
    "views": 5874,
    "collection": "Coleção A",
    "url": "casaco_tannerie_couro.mov"
  },
  {
    "name": "Blazer Cropped Jo",
    "views": 4726,
    "collection": "Coleção A",
    "url": "blazer_cropped_jo.mp4"
  },
  {
    "name": "VESTIDO LONGO PINK MALDIVAS",
    "views": 9150,
    "collection": "Coleção B",
    "url": "vestido_longo_pink_maldivas.MOV"
  },
  {
    "name": "VESTIDO MALDIVAS AZUL ROYAL",
    "views": 4849,
    "collection": "Coleção B",
    "url": "vestido_maldivas_azul_royal.webm"
  },
  {
    "name": "Mocassim Verde em Couro com Bridão Dourado | Giulia Domna",
    "views": 8416,
    "collection": "Coleção B",
    "url": "mocassim_verde_em_couro_com_bridão_dourado_giulia_domna.mov"
  },
  {
    "name": "VESTIDO LONGO PRETO  PAMPLONA",
    "views": 10542,
    "collection": "Coleção B",
    "url": "vestido_longo_preto__pamplona_.mp4"
  },
  {
    "name": "Combo Kit + Curso Hydra Gloss",
    "views": 9120,
    "collection": "Coleção B",
    "url": "combo_kit__curso_hydra_gloss.MOV"
  },
  {
    "name": "Blusa Aleha",
    "views": 7958,
    "collection": "Coleção B",
    "url": "blusa_aleha.webm"
  },
  {
    "name": "VESTIDO AQUAMARINE VERDE LIMA",
    "views": 6522,
    "collection": "Coleção B",
    "url": "vestido_aquamarine_verde_lima.mov"
  },
  {
    "name": "Combo  Kit + Curso Reconstrução de Sobrancelhas",
    "views": 10528,
    "collection": "Coleção B",
    "url": "combo__kit__curso_reconstrução_de_sobrancelhas.mov"
  },
  {
    "name": "Macaquinho Daiany",
    "views": 2220,
    "collection": "Coleção B",
    "url": "macaquinho_daiany.mp4"
  },
  {
    "name": "Vestido Gola Alice",
    "views": 9031,
    "collection": "Coleção C",
    "url": "vestido_gola_alice.MOV"
  },
  {
    "name": "Vestido Nati Vozza",
    "views": 1022,
    "collection": "Coleção C",
    "url": "vestido_nati_vozza.webm"
  }
]
